{
	"title":"Knots Landing",
	"genre":"",
	"creators":["David Jacobs"],
	"cast":["Teri Austin","Alec Baldwin","Tonya Crowe","William Devane","Kevin Dobson","Stacy Galina","Julie Harris","Lisa Hartman","James Houghton","Kim Lankford","Michele Lee","Claudia Lonow","Constance McCashin","Donna Mills","Don Murray","Kathleen Noone","Patrick Petersen","Michelle Phillips","John Pleshette","Larry Riley","Ted Shackelford","Douglas Sheehan","Nicollette Sheridan","Joan Van Ark"],
	"country_of_origin":"USA",
	"seasons":14,
	"episodes":344,
	"start_date":"",
	"end_date":""
}